{"cameraMode":{"drawMode":0,"name":"Shaded","section":"Shading Mode"},"sceneLighting":true,"audioPlay":false,"sceneViewState":{"m_AlwaysRefresh":false,"showFog":true,"showSkybox":true,"showFlares":true,"showImageEffects":true,"showParticleSystems":true,"showVisualEffectGraphs":true,"m_FxEnabled":true},"in2DMode":false,"pivot":{"x":7.723681449890137,"y":-1.3265080451965333,"z":8.229700088500977},"rotation":{"x":0.14571243524551392,"y":0.3781701326370239,"z":-0.06040767952799797,"w":0.9122095704078674},"size":10.073260307312012,"orthographic":false}